statannot/StatResult.py
statannot/__init__.py
statannot/_version.py
statannot/statannot.py
statannot/utils.py
statannot-0.2.3.dist-info/LICENSE
statannot-0.2.3.dist-info/METADATA
statannot-0.2.3.dist-info/WHEEL
statannot-0.2.3.dist-info/top_level.txt
statannot-0.2.3.dist-info/RECORD
