Metadata-Version: 2.1
Name: statannot
Version: 0.2.3
Summary: add statistical annotations on an existing boxplot/barplot generated by seaborn.
Home-page: https://github.com/webermarcolivier/statannot
Author: Marc Weber
Author-email: webermarcolivier@gmail.com
License: UNKNOWN
Platform: UNKNOWN
Classifier: Programming Language :: Python :: 3
Classifier: License :: OSI Approved :: MIT License
Classifier: Operating System :: OS Independent
Requires-Python: >=3.5
